TracSQL-0.3.dist-info/DESCRIPTION.rst
TracSQL-0.3.dist-info/METADATA
TracSQL-0.3.dist-info/RECORD
TracSQL-0.3.dist-info/WHEEL
TracSQL-0.3.dist-info/dependency_links.txt
TracSQL-0.3.dist-info/entry_points.txt
TracSQL-0.3.dist-info/metadata.json
TracSQL-0.3.dist-info/top_level.txt
tracsql/__init__.py
tracsql/web_ui.py
tracsql/htdocs/common.css
tracsql/htdocs/jquery-1.6.3.min.js
tracsql/templates/schema.html
tracsql/templates/sql.html
