Metadata-Version: 2.0
Name: TracSQL
Version: 0.3
Summary: A Trac plugin for querying the project database
Home-page: http://github.com/mrjbq7/tracsql
Author: John Benediktsson
Author-email: mrjbq7@gmail.com
License: UNKNOWN
Download-URL: http://github.com/mrjbq7/tracsql/zipball/master#egg=TracSQL-0.3
Platform: UNKNOWN
